libllm/__init__.py
libllm/interop.py
libllm/llm-core.dll
pylibllm-1.3.1.dist-info/METADATA
pylibllm-1.3.1.dist-info/WHEEL
pylibllm-1.3.1.dist-info/top_level.txt
pylibllm-1.3.1.dist-info/RECORD
