Metadata-Version: 2.1
Name: pylibllm
Version: 1.3.1
Summary: libLLM is an open-source project tailored for efficient inference of large language models (LLMs).
Home-page: https://github.com/ling0322/libllm
Author: ling0322
Author-email: ling032x@gmail.com
License: MIT
Classifier: Programming Language :: Python :: 3
Classifier: Programming Language :: Python :: 3.6
Classifier: Programming Language :: Python :: 3.7
Classifier: Programming Language :: Python :: 3.8
Classifier: Programming Language :: Python :: 3.9
Classifier: Programming Language :: Python :: 3.10
Classifier: Programming Language :: Python :: 3.11
Classifier: Programming Language :: Python :: 3.12
Classifier: License :: OSI Approved :: MIT License
Classifier: Operating System :: OS Independent
Requires-Python: >=3.6
